{"question": "Choose the right meaning:", "top_field": [[["aling", {"color": "black"}], ["uq", {"color": "grey"}]], [["an", {"color": "black"}], ["'uq", {"color": "grey"}]], [["aqui", {"color": "black"}], ["guq", {"color": "grey"}]], [["piiyua", {"color": "black"}], ["guq", {"color": "grey"}]], [["aurr", {"color": "black"}], ["uq", {"color": "grey"}]], [["ayag", {"color": "black"}], ["tuq", {"color": "grey"}]], [["cali", {"color": "black"}], ["uq", {"color": "grey"}]], [["cenirt", {"color": "black"}], ["uq", {"color": "grey"}]], [["cuka", {"color": "black"}], ["uq", {"color": "grey"}]], [["elit", {"color": "black"}], ["uq", {"color": "grey"}]]], "bottom_field": [[["      ", {"color": "black"}], ["he is ___________", {"color": "grey", "fontStyle": "italic"}]], [["      ", {"color": "black"}], ["he is ___________", {"color": "grey", "fontStyle": "italic"}]], [["      ", {"color": "black"}], ["he is ___________", {"color": "grey", "fontStyle": "italic"}]], [["      ", {"color": "black"}], ["he is ___________", {"color": "grey", "fontStyle": "italic"}]], [["      ", {"color": "black"}], ["he is ___________", {"color": "grey", "fontStyle": "italic"}]], [["      ", {"color": "black"}], ["he is ___________", {"color": "grey", "fontStyle": "italic"}]], [["      ", {"color": "black"}], ["he is ___________", {"color": "grey", "fontStyle": "italic"}]], [["      ", {"color": "black"}], ["he is ___________", {"color": "grey", "fontStyle": "italic"}]], [["      ", {"color": "black"}], ["he is ___________", {"color": "grey", "fontStyle": "italic"}]], [["      ", {"color": "black"}], ["he is ___________", {"color": "grey", "fontStyle": "italic"}]]], "correct_answer": [[["afraid", {"color": "grey", "fontStyle": "italic"}]], [["going out", {"color": "grey", "fontStyle": "italic"}]], [["playing", {"color": "grey", "fontStyle": "italic"}]], [["good/nice", {"color": "grey", "fontStyle": "italic"}]], [["crawling", {"color": "grey", "fontStyle": "italic"}]], [["leaving", {"color": "grey", "fontStyle": "italic"}]], [["working", {"color": "grey", "fontStyle": "italic"}]], [["visiting", {"color": "grey", "fontStyle": "italic"}]], [["fast", {"color": "grey", "fontStyle": "italic"}]], [["learning", {"color": "grey", "fontStyle": "italic"}]]], "simple_correct_answer": ["afraid", "going out", "playing", "good/nice", "crawling", "leaving", "working", "visiting", "fast", "learning"], "question_specific_options": [[9, 2]], "same_options": [], "option_type": "question_specific", "entries_wav": ["alinguq.wav", "anuq.wav", "aquiguq.wav", "assirtuq.wav", "aurruq.wav", "ayagtuq.wav", "caliuq.wav", "cenirtuq.wav", "cukauq.wav", "elituq.wav", "inartuq.wav", "iqauq.wav"], "display_wav_type": "question", "progress_bar_type": 1, "incorrect_answer_response": [[], [], [], [], [], [], [], [], [], []], "correct_answer_response": [[], [], [], [], [], [], [], [], [], []], "correct_answer_all": [["You are correct!", "'color='black' fontStyle='regular' as='h4' align='left'"], ["", ""]], "incorrect_answer_all": [["The correct answer is:", "'color='black' fontStyle='regular' as='h4' align='left'"], ["", ""]]}